shanti/__init__.py
shanti/shanti.py
shanti/version.py
shanti-0.1.3.data/data/license-files/LICENSE
shanti-0.1.3.dist-info/licenses/LICENSE
shanti-0.1.3.dist-info/METADATA
shanti-0.1.3.dist-info/WHEEL
shanti-0.1.3.dist-info/top_level.txt
shanti-0.1.3.dist-info/RECORD
