Metadata-Version: 2.4
Name: shanti
Version: 0.1.3
Summary: create SHarable, interactive, stANdalone html dashboard from Tabular proteomIcs data
Author: Nara Marella
License-Expression: GPL-3.0-or-later
Project-URL: Homepage, https://github.com/n3m4u/shanti
Project-URL: Issues, https://github.com/n3m4u/shanti/issues
Classifier: Programming Language :: Python :: 3
Classifier: Operating System :: OS Independent
Requires-Python: >=3.9
License-File: LICENSE
Requires-Dist: pandas
Requires-Dist: bokeh
Requires-Dist: openpyxl
Requires-Dist: scipy
Requires-Dist: numpy
Dynamic: license-file
